pybi/__index.py
pybi/__init__.py
pybi/app.py
pybi/core/__init__.py
pybi/core/dataSource.py
pybi/core/sql.py
pybi/core/uiResource.py
pybi/core/webResources.py
pybi/core/components/__init__.py
pybi/core/components/component.py
pybi/core/components/componentTag.py
pybi/core/components/containerComponent.py
pybi/core/components/mermaid.py
pybi/core/components/staticComponent.py
pybi/core/components/reactiveComponent/__init__.py
pybi/core/components/reactiveComponent/base.py
pybi/core/components/reactiveComponent/checkbox.py
pybi/core/components/reactiveComponent/echarts.py
pybi/core/components/reactiveComponent/input.py
pybi/core/components/reactiveComponent/markdown.py
pybi/core/components/reactiveComponent/numberSlider.py
pybi/core/components/reactiveComponent/slicer.py
pybi/core/components/reactiveComponent/table.py
pybi/core/components/reactiveComponent/textValue.py
pybi/core/styles/__init__.py
pybi/core/styles/styleTag.py
pybi/core/styles/styles.py
pybi/core/styles/utils.py
pybi/core/styles/tailwindStyles/__init__.py
pybi/core/styles/tailwindStyles/boxShadow.py
pybi/core/styles/tailwindStyles/textAlign.py
pybi/core/styles/tailwindStyles/textColor.py
pybi/core/styles/tailwindStyles/textSize.py
pybi/easyEcharts/__init__.py
pybi/easyEcharts/bar.py
pybi/easyEcharts/base.py
pybi/easyEcharts/candlestick.py
pybi/easyEcharts/dictChart.py
pybi/easyEcharts/line.py
pybi/easyEcharts/map.py
pybi/easyEcharts/pie.py
pybi/easyEcharts/radar.py
pybi/easyEcharts/scatter.py
pybi/easyEcharts/utils.py
pybi/icons/__init__.py
pybi/icons/iconManager.py
pybi/icons/material_icons.py
pybi/static/echarts.min.js
pybi/static/echartsCps-style.css
pybi/static/echartsCps.iife.js
pybi/static/elementCps-style.css
pybi/static/elementCps.iife.js
pybi/static/experimentalCps-style.css
pybi/static/experimentalCps.iife.js
pybi/static/mermaidCps-style.css
pybi/static/mermaidCps.iife.js
pybi/static/province_map_full.json
pybi/static/sysApp-style.css
pybi/static/sysApp.iife.js
pybi_next-0.4.24.dist-info/LICENSE
pybi_next-0.4.24.dist-info/METADATA
pybi_next-0.4.24.dist-info/WHEEL
pybi_next-0.4.24.dist-info/top_level.txt
pybi_next-0.4.24.dist-info/RECORD
