Metadata-Version: 2.1
Name: pybi-next
Version: 0.4.24
Summary: ...
Home-page: 
Author: carson_jia
Author-email: 568166495@qq.com
License: MIT license
Keywords: pybi,vision,BI,report
Classifier: Intended Audience :: Developers
Classifier: License :: OSI Approved :: MIT License
Classifier: Natural Language :: English
Classifier: Programming Language :: Python :: 3.7
Classifier: Programming Language :: Python :: 3.8
Requires-Python: >=3.7
License-File: LICENSE
Requires-Dist: pandas
Requires-Dist: simplejson
Requires-Dist: jinja2
